odoo/addons/ssi_mail/README.rst
odoo/addons/ssi_mail/__init__.py
odoo/addons/ssi_mail/__manifest__.py
odoo/addons/ssi_mail/static/description/icon.png
odoo/addons/ssi_mail/wizard/__init__.py
odoo/addons/ssi_mail/wizard/mail_wizard_invite.py
odoo/addons/ssi_mail/wizard/mail_wizard_invite_views.xml
odoo14_addon_ssi_mail-14.0.1.1.0.dist-info/METADATA
odoo14_addon_ssi_mail-14.0.1.1.0.dist-info/WHEEL
odoo14_addon_ssi_mail-14.0.1.1.0.dist-info/top_level.txt
odoo14_addon_ssi_mail-14.0.1.1.0.dist-info/RECORD
